pio/__init__.py
pio/client.py
pio/error/api_error.py
pio/model/environment.py
pio/model/get.py
pio/model/oauth.py
pio/model/report.py
pio/model/service.py
pio/oauth.py
pio/pio.py
pio/utility/json_encoder.py
placements_io-0.0.2.dist-info/LICENSE
placements_io-0.0.2.dist-info/METADATA
placements_io-0.0.2.dist-info/WHEEL
placements_io-0.0.2.dist-info/RECORD
