Metadata-Version: 2.1
Name: placements-io
Version: 0.0.2
Summary: Placements.io Python Software Development Kit
Home-page: https://placements.io
License: MIT
Author: Placements.io
Requires-Python: >=3.12,<4.0
Classifier: License :: OSI Approved :: MIT License
Classifier: Programming Language :: Python :: 3
Classifier: Programming Language :: Python :: 3.12
Requires-Dist: httpx (>=0.27.2,<0.28.0)
Project-URL: Documentation, https://api.placements.io/doc/#resources
Project-URL: Repository, https://github.com/placementsapp/pio-python-sdk
